drftokit/__init__.py
drftokit/only/__init__.py
drftokit/only/only.py
drftokit-0.1.7.dist-info/WHEEL
drftokit-0.1.7.dist-info/METADATA
drftokit-0.1.7.dist-info/RECORD
