Metadata-Version: 2.1
Name: drftokit
Version: 0.1.7
Summary: DRF tokit.
License: MIT
Author: pytools
Author-email: hyhlinux@gmail.com
Requires-Python: >=3.8
Classifier: License :: OSI Approved :: MIT License
Classifier: Programming Language :: Python :: 3
Classifier: Programming Language :: Python :: 3.8
Classifier: Programming Language :: Python :: 3.9
Classifier: Programming Language :: Python :: 3.10
Classifier: Programming Language :: Python :: 3.11
Requires-Dist: django (>=2.2)
Requires-Dist: djangorestframework (>=3.11)
